tooljob/__init__.py
tooljob/batch_class.py
tooljob/py.typed
tooljob/spec/__init__.py
tooljob/spec/typedefs.py
tooljob/trackers/__init__.py
tooljob/trackers/bucket_tracker.py
tooljob/trackers/file_tracker.py
tooljob/trackers/multifile_tracker.py
tooljob/trackers/sql_tracker.py
tooljob/trackers/tracker.py
tooljob/trackers/tracker_utils.py
tooljob-0.1.6.dist-info/WHEEL
tooljob-0.1.6.dist-info/METADATA
tooljob-0.1.6.dist-info/RECORD
