Metadata-Version: 2.1
Name: tooljob
Version: 0.1.6
Summary: utilities for orchestrating batches of jobs
Requires-Python: >=3.7
Requires-Dist: typing-extensions >=4.2.0, <5
Requires-Dist: tqdm >=4.65.0, <5
Requires-Dist: toolstr >=0.9.3, <0.10
Requires-Dist: tooltime >=0.2.9, <0.3
